<?xml version="1.0" encoding="utf-8"?>
<data>
  <data>
    <schedule_entry>
      <channel_id_requested>7</channel_id_requested>
      <date_requested>Current Day (KST approx: 20250816)</date_requested>
      <date_displayed>2025-08-16</date_displayed>
      <channel_name>KBS2</channel_name>
      <channel_logo_url>https://tv.kt.com/relatedmaterial/ch_logo/skylife/a813974300226102119.png</channel_logo_url>
      <programs>
        <program>
          <time>00:35</time>
          <title>놓친예능 따라잡기</title>
          <is_on_air>False</is_on_air>
          <icons>
            <icon>15세 이상 시청 가능</icon>
            <icon>Hd</icon>
            <icon>Icon (src: /src/images/kt_tv/icons/icon_18x18_cap.png)</icon>
          </icons>
          <genre>연예/오락</genre>
        </program>
        <program>
          <time>01:05</time>
          <title>방송 시간이 아닙니다(5시부터 방송 예정)</title>
          <is_on_air>False</is_on_air>
          <icons>
            <icon>전체 시청 가능</icon>
            <icon>Sd</icon>
          </icons>
          <genre>교양/정보</genre>
        </program>
        <program>
          <time>05:00</time>
          <title>사랑의 가족</title>
          <is_on_air>False</is_on_air>
          <icons>
            <icon>전체 시청 가능</icon>
            <icon>Hd</icon>
            <icon>Icon (src: /src/images/kt_tv/icons/icon_18x18_desc.png)</icon>
            <icon>Icon (src: /src/images/kt_tv/icons/icon_18x18_sign.png)</icon>
            <icon>Icon (src: /src/images/kt_tv/icons/icon_18x18_cap.png)</icon>
          </icons>
          <genre>교양/정보</genre>
        </program>
        <program>
          <time>05:50</time>
          <title>세상의 모든 다큐</title>
          <is_on_air>False</is_on_air>
          <icons>
            <icon>전체 시청 가능</icon>
            <icon>Hd</icon>
            <icon>Icon (src: /src/images/kt_tv/icons/icon_18x18_desc.png)</icon>
            <icon>Icon (src: /src/images/kt_tv/icons/icon_18x18_cap.png)</icon>
          </icons>
          <genre>시사/다큐</genre>
        </program>
        <program>
          <time>06:40</time>
          <title>트레킹노트 세상을 걷다 스페셜</title>
          <is_on_air>False</is_on_air>
          <icons>
            <icon>전체 시청 가능</icon>
            <icon>Hd</icon>
            <icon>Icon (src: /src/images/kt_tv/icons/icon_18x18_cap.png)</icon>
          </icons>
          <genre>시사/다큐</genre>
        </program>
        <program>
          <time>07:20</time>
          <title>박원숙의 같이 삽시다</title>
          <is_on_air>False</is_on_air>
          <icons>
            <icon>15세 이상 시청 가능</icon>
            <icon>Hd</icon>
            <icon>Icon (src: /src/images/kt_tv/icons/icon_18x18_cap.png)</icon>
          </icons>
          <genre>연예/오락</genre>
        </program>
        <program>
          <time>08:40</time>
          <title>사장님 귀는 당나귀 귀</title>
          <is_on_air>False</is_on_air>
          <icons>
            <icon>15세 이상 시청 가능</icon>
            <icon>Hd</icon>
            <icon>Icon (src: /src/images/kt_tv/icons/icon_18x18_cap.png)</icon>
          </icons>
          <genre>연예/오락</genre>
        </program>
        <program>
          <time>10:10</time>
          <title>영화가 좋다</title>
          <is_on_air>False</is_on_air>
          <icons>
            <icon>15세 이상 시청 가능</icon>
            <icon>Hd</icon>
            <icon>Icon (src: /src/images/kt_tv/icons/icon_18x18_cap.png)</icon>
          </icons>
          <genre>연예/오락</genre>
        </program>
        <program>
          <time>11:20</time>
          <title>크레이지 리치 코리안</title>
          <is_on_air>False</is_on_air>
          <icons>
            <icon>15세 이상 시청 가능</icon>
            <icon>Hd</icon>
            <icon>Icon (src: /src/images/kt_tv/icons/icon_18x18_cap.png)</icon>
          </icons>
          <genre>연예/오락</genre>
        </program>
        <program>
          <time>12:55</time>
          <title>수목드라마 내 여자친구는 상남자</title>
          <is_on_air>False</is_on_air>
          <icons>
            <icon>15세 이상 시청 가능</icon>
            <icon>Hd</icon>
            <icon>Icon (src: /src/images/kt_tv/icons/icon_18x18_desc.png)</icon>
            <icon>Icon (src: /src/images/kt_tv/icons/icon_18x18_cap.png)</icon>
          </icons>
          <genre>드라마</genre>
        </program>
        <program>
          <time>14:10</time>
          <title>수목드라마 내 여자친구는 상남자</title>
          <is_on_air>False</is_on_air>
          <icons>
            <icon>15세 이상 시청 가능</icon>
            <icon>Hd</icon>
            <icon>Icon (src: /src/images/kt_tv/icons/icon_18x18_desc.png)</icon>
            <icon>Icon (src: /src/images/kt_tv/icons/icon_18x18_cap.png)</icon>
          </icons>
          <genre>드라마</genre>
        </program>
        <program>
          <time>15:25</time>
          <title>주말드라마 화려한 날들</title>
          <is_on_air>False</is_on_air>
          <icons>
            <icon>15세 이상 시청 가능</icon>
            <icon>Hd</icon>
            <icon>Icon (src: /src/images/kt_tv/icons/icon_18x18_cap.png)</icon>
          </icons>
          <genre>드라마</genre>
        </program>
        <program>
          <time>16:45</time>
          <title>주말드라마 화려한 날들</title>
          <is_on_air>True</is_on_air>
          <icons>
            <icon>15세 이상 시청 가능</icon>
            <icon>Hd</icon>
            <icon>Icon (src: /src/images/kt_tv/icons/icon_18x18_cap.png)</icon>
          </icons>
          <genre>드라마</genre>
        </program>
        <program>
          <time>18:05</time>
          <title>불후의 명곡</title>
          <is_on_air>False</is_on_air>
          <icons>
            <icon>15세 이상 시청 가능</icon>
            <icon>Hd</icon>
            <icon>Icon (src: /src/images/kt_tv/icons/icon_18x18_cap.png)</icon>
          </icons>
          <genre>연예/오락</genre>
        </program>
        <program>
          <time>20:00</time>
          <title>주말드라마 화려한 날들</title>
          <is_on_air>False</is_on_air>
          <icons>
            <icon>15세 이상 시청 가능</icon>
            <icon>Hd</icon>
            <icon>Icon (src: /src/images/kt_tv/icons/icon_18x18_cap.png)</icon>
          </icons>
          <genre>드라마</genre>
        </program>
        <program>
          <time>21:20</time>
          <title>살림하는 남자들</title>
          <is_on_air>False</is_on_air>
          <icons>
            <icon>15세 이상 시청 가능</icon>
            <icon>Hd</icon>
            <icon>Icon (src: /src/images/kt_tv/icons/icon_18x18_cap.png)</icon>
          </icons>
          <genre>연예/오락</genre>
        </program>
        <program>
          <time>22:40</time>
          <title>내편하자 4</title>
          <is_on_air>False</is_on_air>
          <icons>
            <icon>15세 이상 시청 가능</icon>
            <icon>Hd</icon>
            <icon>Icon (src: /src/images/kt_tv/icons/icon_18x18_cap.png)</icon>
          </icons>
          <genre>연예/오락</genre>
        </program>
        <program>
          <time>23:45</time>
          <title>스튜디오 K</title>
          <is_on_air>False</is_on_air>
          <icons>
            <icon>15세 이상 시청 가능</icon>
            <icon>Hd</icon>
            <icon>Icon (src: /src/images/kt_tv/icons/icon_18x18_cap.png)</icon>
          </icons>
          <genre>연예/오락</genre>
        </program>
      </programs>
      <script_run_epoch_utc>1755332366</script_run_epoch_utc>
      <script_run_iso_utc>2025-08-16T08:19:26.562500+00:00</script_run_iso_utc>
      <schedule_context_message>Displaying schedule for 2025-08-16.</schedule_context_message>
    </schedule_entry>
  </data>
</data>
